dmocker/__init__.py
dmocker/main.py
dmocker/exceptions/custom.py
dmocker/exceptions/validator.py
dmocker/src/arguments.py
dmocker/src/container_info.py
dmocker/src/fetcher.py
dmocker-0.0.2.dist-info/LICENSE
dmocker-0.0.2.dist-info/METADATA
dmocker-0.0.2.dist-info/WHEEL
dmocker-0.0.2.dist-info/entry_points.txt
dmocker-0.0.2.dist-info/top_level.txt
dmocker-0.0.2.dist-info/RECORD
