Metadata-Version: 2.1
Name: dmocker
Version: 0.0.2
Summary: Remote Docker control
Author-email: strecobyasha <strecobyasha@protonmail.com>
Project-URL: Homepage, https://github.com/strecobyasha/dmocker
Project-URL: Issues, https://github.com/strecobyasha/dmocker/issues
Classifier: Programming Language :: Python :: 3
Classifier: License :: OSI Approved :: MIT License
Classifier: Operating System :: OS Independent
Requires-Python: >=3.8
License-File: LICENSE
